dev_mcp/__init__.py
dev_mcp/cli.py
dev_mcp/server.py
dev_mcp/tools/__init__.py
dev_mcp/tools/common/__init__.py
dev_mcp/tools/common/context.py
dev_mcp/tools/common/permissions.py
dev_mcp/tools/common/thinking.py
dev_mcp/tools/common/validation.py
dev_mcp/tools/filesystem/__init__.py
dev_mcp/tools/filesystem/file_operations.py
dev_mcp/tools/jupyter/__init__.py
dev_mcp/tools/jupyter/notebook_operations.py
dev_mcp/tools/project/__init__.py
dev_mcp/tools/project/analysis.py
dev_mcp/tools/shell/__init__.py
dev_mcp/tools/shell/command_executor.py
hanzo_dev_mcp-0.1.19.dist-info/licenses/LICENSE
hanzo_dev_mcp-0.1.19.dist-info/METADATA
hanzo_dev_mcp-0.1.19.dist-info/WHEEL
hanzo_dev_mcp-0.1.19.dist-info/entry_points.txt
hanzo_dev_mcp-0.1.19.dist-info/top_level.txt
hanzo_dev_mcp-0.1.19.dist-info/RECORD
