Metadata-Version: 2.4
Name: hanzo-dev-mcp
Version: 0.1.19
Summary: MCP implementation of Hanzo Dev capabilities
Author-email: Hanzo Dev <dev@hanzo.ai>
License: MIT
Classifier: Programming Language :: Python :: 3
Classifier: License :: OSI Approved :: MIT License
Classifier: Operating System :: OS Independent
Requires-Python: >=3.13
License-File: LICENSE
Requires-Dist: mcp>=1.3.0
Requires-Dist: httpx>=0.27.0
Requires-Dist: uvicorn>=0.23.1
Requires-Dist: mcp
Requires-Dist: pytest
Provides-Extra: dev
Requires-Dist: pytest>=7.0.0; extra == "dev"
Requires-Dist: pytest-cov>=4.1.0; extra == "dev"
Requires-Dist: ruff>=0.1.0; extra == "dev"
Requires-Dist: black>=23.3.0; extra == "dev"
Provides-Extra: test
Requires-Dist: pytest>=7.0.0; extra == "test"
Requires-Dist: pytest-cov>=4.1.0; extra == "test"
Requires-Dist: pytest-mock>=3.10.0; extra == "test"
Requires-Dist: pytest-asyncio>=0.25.3; extra == "test"
Requires-Dist: twisted; extra == "test"
Provides-Extra: performance
Requires-Dist: ujson>=5.7.0; extra == "performance"
Requires-Dist: orjson>=3.9.0; extra == "performance"
Dynamic: license-file
